<?xml version="1.0" encoding="UTF-8" standalone="no"?>
<sbml 
  xmlns="http://www.sbml.org/sbml/level2/version4" 
  xmlns:xhtml="http://www.w3.org/1999/xhtml" 
  level="2" version="4"
  >
  <annotation>
    <hetalang:hasMeta xmlns:hetalang="http://hetalang.github.io/sbml/annotation" hetalang:metaVersion="1.0">{"toolName":"heta-compiler","toolVersion":"0.12.0-beta.1","createdAt":"2026-06-08T07:07:28.513Z","platformId":"template","platformVersion":"v0.1.0","namespaceId":"nameless","format":"sbml"}</hetalang:hasMeta> 
  </annotation>
  <model
    id="nameless"
    >
    

  
    <listOfCompartments>
      <compartment
        id="comp1"
        constant="false"
        size="1"
        >
      </compartment>
    </listOfCompartments>
  
    <listOfSpecies>
      <species
        id="A"
        compartment="comp1"
        constant="false"
        boundaryCondition="false"
        hasOnlySubstanceUnits="false"
        initialConcentration="5"
        >
      </species>
      <species
        id="B"
        compartment="comp1"
        constant="false"
        boundaryCondition="false"
        hasOnlySubstanceUnits="false"
        initialConcentration="0"
        >
      </species>
    </listOfSpecies>
  
    <listOfParameters>
      <parameter
        id="Vmax"
        constant="true"
        value="1.2"
        >
      </parameter>
      <parameter
        id="Km"
        constant="true"
        value="3.2"
        >
      </parameter>
      <parameter
        id="cond1"
        constant="true"
        value="1.2"
        >
      </parameter>
    </listOfParameters>
  
    <listOfReactions>
      <reaction
        id="r1"
        reversible="false"
        fast="false"
        >
        <listOfReactants>
          <speciesReference species="A" stoichiometry="1"/>
        </listOfReactants>
        <listOfProducts>
          <speciesReference species="B" stoichiometry="1"/>
        </listOfProducts>
        <kineticLaw>
          <math xmlns="http://www.w3.org/1998/Math/MathML"><apply><times/><apply><divide/><apply><times/><ci>Vmax</ci><ci>A</ci></apply><apply><plus/><ci>A</ci><ci>Km</ci></apply></apply><ci>comp1</ci></apply></math>
        </kineticLaw>
      </reaction>
    </listOfReactions>
  
  
  </model>
</sbml>
